MANIFEST.in
README.rst
setup.cfg
setup.py
include/utilities/merge_operators.h
python_rocksdb_iota.egg-info/PKG-INFO
python_rocksdb_iota.egg-info/SOURCES.txt
python_rocksdb_iota.egg-info/dependency_links.txt
python_rocksdb_iota.egg-info/requires.txt
python_rocksdb_iota.egg-info/top_level.txt
rocksdb_iota/__init__.py
rocksdb_iota/_rocksdb.cpp
rocksdb_iota/_rocksdb.pyx
rocksdb_iota/backup.pxd
rocksdb_iota/cache.pxd
rocksdb_iota/comparator.pxd
rocksdb_iota/db.pxd
rocksdb_iota/env.pxd
rocksdb_iota/errors.py
rocksdb_iota/filter_policy.pxd
rocksdb_iota/interfaces.py
rocksdb_iota/iterator.pxd
rocksdb_iota/logger.pxd
rocksdb_iota/memtablerep.pxd
rocksdb_iota/merge_operator.pxd
rocksdb_iota/merge_operators.py
rocksdb_iota/options.pxd
rocksdb_iota/slice_.pxd
rocksdb_iota/slice_transform.pxd
rocksdb_iota/snapshot.pxd
rocksdb_iota/status.pxd
rocksdb_iota/std_memory.pxd
rocksdb_iota/table_factory.pxd
rocksdb_iota/universal_compaction.pxd
rocksdb_iota/cpp/comparator_wrapper.hpp
rocksdb_iota/cpp/filter_policy_wrapper.hpp
rocksdb_iota/cpp/memtable_factories.hpp
rocksdb_iota/cpp/merge_operator_wrapper.hpp
rocksdb_iota/cpp/slice_transform_wrapper.hpp
rocksdb_iota/cpp/utils.hpp
rocksdb_iota/cpp/write_batch_iter_helper.hpp
rocksdb_iota/tests/__init__.py
rocksdb_iota/tests/test_db.py
rocksdb_iota/tests/test_memtable.py
rocksdb_iota/tests/test_options.py