Metadata-Version: 1.1
Name: python-rocksdb-iota
Version: 0.7.2
Summary: Python bindings for RocksDB with IOTA modification
Home-page: https://github.com/mlouielu/python-rocksdb
Author: Louie Lu
Author-email: git@louie.lu
License: BSD License
Keywords: rocksdb,IOTA
Platform: UNKNOWN
Classifier: Development Status :: 3 - Alpha
Classifier: License :: OSI Approved :: BSD License
Classifier: Operating System :: POSIX :: Linux
Classifier: Programming Language :: Python :: 3 :: Only
